{"yesterday": {"freeExpiration": 0, "pangrams": ["outgrown"], "centerLetter": "n", "displayWeekday": "Monday", "id": 7471, "outerLetters": ["g", "o", "r", "t", "u", "w"], "validLetters": ["n", "g", "o", "r", "t", "u", "w"], "answers": ["outgrown", "gong", "goon", "gorgon", "gown", "grown", "grunt", "noon", "noun", "onto", "outgun", "outrun", "outworn", "rung", "runout", "runt", "tong", "toon", "torn", "town", "turn", "turnout", "unto", "unwon", "unworn", "wont", "wonton", "worn", "wrong", "wrung"], "printDate": "2019-12-16", "editor": "Sam Ezersky", "displayDate": "December 16, 2019"}, "today": {"displayWeekday": "Tuesday", "outerLetters": ["a", "j", "l", "m", "r", "y"], "validLetters": ["o", "a", "j", "l", "m", "r", "y"], "answers": ["majorly", "alloy", "ammo", "amoral", "amorally", "armor", "armory", "aroma", "arroyo", "jolly", "loam", "loamy", "loll", "loom", "lorry", "loyal", "loyally", "major", "marjoram", "mayo", "mayor", "mayoral", "mojo", "molar", "moll", "momma", "mommy", "moola", "moor", "moral", "morally", "moray", "oral", "orally", "roam", "roar", "roll", "room", "roomy", "royal", "royally"], "printDate": "2019-12-17", "expiration": 1576656000, "freeExpiration": 0, "centerLetter": "o", "id": 2502, "pangrams": ["majorly"], "displayDate": "December 17, 2019", "editor": "Sam Ezersky"}}